my_project/__init__.py
my_project/module1.py
my_project/module2.py
df_first_project_for_test-0.0.1.dist-info/METADATA
df_first_project_for_test-0.0.1.dist-info/WHEEL
df_first_project_for_test-0.0.1.dist-info/top_level.txt
df_first_project_for_test-0.0.1.dist-info/RECORD
