Metadata-Version: 2.1
Name: df-first-project-for-test
Version: 0.0.1
Summary: A brief description of your project
Home-page: https://github.com/yourusername/my_project
Author: Your Name
Author-email: your.email@example.com
Classifier: Programming Language :: Python :: 3
Classifier: License :: OSI Approved :: MIT License
Classifier: Operating System :: OS Independent
Requires-Python: >=3.6
